kafkatop.py
kafkatop-1.16.dist-info/METADATA
kafkatop-1.16.dist-info/WHEEL
kafkatop-1.16.dist-info/entry_points.txt
kafkatop-1.16.dist-info/top_level.txt
kafkatop-1.16.dist-info/RECORD
