Metadata-Version: 2.4
Name: kafkatop
Version: 1.16
Summary: A real-time monitoring tool for Apache Kafka that displays consumer lag and event rates
Author: Spiros Ioannou
License-Expression: MIT
Project-URL: Homepage, https://github.com/sivann/kafkatop
Project-URL: Repository, https://github.com/sivann/kafkatop
Keywords: kafka,monitoring,consumer,lag,real-time
Classifier: Development Status :: 5 - Production/Stable
Classifier: Intended Audience :: Developers
Classifier: Intended Audience :: System Administrators
Classifier: Operating System :: OS Independent
Classifier: Programming Language :: Python :: 3
Classifier: Programming Language :: Python :: 3.9
Classifier: Programming Language :: Python :: 3.10
Classifier: Programming Language :: Python :: 3.11
Classifier: Programming Language :: Python :: 3.12
Classifier: Programming Language :: Python :: 3.13
Classifier: Topic :: System :: Monitoring
Classifier: Topic :: Software Development :: Libraries :: Python Modules
Requires-Python: >=3.9
Requires-Dist: confluent-kafka
Requires-Dist: humanize
Requires-Dist: rich
Requires-Dist: readchar
Requires-Dist: markdown-it-py==3.0.0; python_version == "3.9"
Requires-Dist: markdown-it-py; python_version >= "3.10"
Provides-Extra: dev
Requires-Dist: wheel; extra == "dev"
Requires-Dist: twine; extra == "dev"
Requires-Dist: build; extra == "dev"
Requires-Dist: pytest; extra == "dev"
Requires-Dist: coverage; extra == "dev"
